fpl_data_loader/__init__.py
fpl_data_loader/load.py
fpl_data_loader/transform.py
fpl_data_loader/utils.py
fpl_data_loader-0.3.2.dist-info/WHEEL
fpl_data_loader-0.3.2.dist-info/METADATA
fpl_data_loader-0.3.2.dist-info/RECORD
