Metadata-Version: 2.3
Name: fpl-data-loader
Version: 0.3.2
Summary: Tools for working with Fantasy Premier League data
Author: James Leslie
Author-email: James Leslie <contactjamesleslie@gmail.com>
Requires-Dist: numpy>=2.0.2
Requires-Dist: pandas>=2.3.2
Requires-Dist: requests>=2.32.5
Requires-Dist: tqdm>=4.67.1
Requires-Python: >=3.9
